{
    "meta_info": {
        "user_query": "CT, MRI 등의 의료 영상을 분석하여 질병 진단을 돕는 인공지능 모델을 구축하고 최적화하려면 어떤 과정이 필요할까요?",
        "expanded_query": null,
        "given_departments": null,
        "selected_departments": null
    },
    "recommendations": [
        {
            "id": 4651,
            "name": "인간행동과사회환경",
            "student_grade": 1,
            "semester": 2,
            "department_name": "사회복지학과",
            "similarity": 0.13361382915746264
        },
        {
            "id": 793,
            "name": "인공지능",
            "student_grade": 3,
            "semester": 1,
            "department_name": "컴퓨터인공지능학부",
            "similarity": 0.1052730816612732
        },
        {
            "id": 3528,
            "name": "인공지능",
            "student_grade": 3,
            "semester": 2,
            "department_name": "기계설계공학부",
            "similarity": 0.14770027258959126
        },
        {
            "id": 2621,
            "name": "임상영양학",
            "student_grade": 3,
            "semester": 2,
            "department_name": "식품영양학과",
            "similarity": 0.13022524398917393
        },
        {
            "id": 4575,
            "name": "딥러닝",
            "student_grade": 3,
            "semester": 2,
            "department_name": "전자공학부",
            "similarity": 0.10386202831102756
        },
        {
            "id": 557,
            "name": "의료영상 2",
            "student_grade": 4,
            "semester": 1,
            "department_name": "바이오메디컬공학부",
            "similarity": 0.1684411161533498
        },
        {
            "id": 601,
            "name": "동물진단과학",
            "student_grade": 4,
            "semester": 1,
            "department_name": "동물생명공학과",
            "similarity": 0.15689686205456205
        },
        {
            "id": 717,
            "name": "병원정보시스템",
            "student_grade": 4,
            "semester": 1,
            "department_name": "바이오메디컬공학부",
            "similarity": 0.14952263921562894
        },
        {
            "id": 3741,
            "name": "건강심리학",
            "student_grade": 4,
            "semester": 2,
            "department_name": "심리학과",
            "similarity": 0.11627244400134348
        },
        {
            "id": 4104,
            "name": "회계사",
            "student_grade": 4,
            "semester": 2,
            "department_name": "회계학과",
            "similarity": 0.10449691143407668
        }
    ]
}