{
    "meta_info": {
        "user_query": "항공기 및 드론의 공기역학적 성능을 분석하고 최적화하는 항공 역학 엔지니어(Aerodynamics Engineer)가 되고 싶어요. 필요한 과정은 무엇인가요?",
        "expanded_query": "항공기 및 드론의 공기역학적 성능을 분석하고 최적화하는 항공 역학 엔지니어(Aerodynamics Engineer)가 되고 싶어요. 필요한 과정은 무엇인가요? 항공 역학 분야에서의 이론과 응용 능력을 갖춘 전문가 양성 항공 역학 엔지니어로서의 전문적 지식과 기술을 활용하여 항공기 및 드론의 성능을 최적화 항공 공학 항공 역학 엔지니어 (Aerodynamics Engineer) 항공기 및 드론의 공기역학적 특성을 분석하고 최적화를 통해 비행 성능을 향상시키며, 효율적인 비행을 위해 새로운 설계 솔루션을 개발 공기역학적 데이터 분석, 설계 프로세스 최적화, 성능 평가 및 개선 방안 제시, 시뮬레이션 및 실험 수행 CFD(Computational Fluid Dynamics) 시뮬레이션, 공기역학 이론 이해, 설계 소프트웨어 사용 능력 공기역학 실험 설계 및 분석, 문제 해결 능력, 팀 협업 및 의사소통 능력 유체 역학, 열역학, 비행 동역학 공기역학 설계 및 테스트 기법, 비행기 및 드론 구조  CFD 소프트웨어 활용, 실험적 데이터 해석 기술",
        "given_departments": null,
        "selected_departments": null
    },
    "recommendations": [
        {
            "id": 3196,
            "name": "디지털논리공학",
            "student_grade": 1,
            "semester": 2,
            "department_name": "전기공학과",
            "similarity": 0.10695171467573426
        },
        {
            "id": 904,
            "name": "역학 1",
            "student_grade": 2,
            "semester": 1,
            "department_name": "물리학과",
            "similarity": 0.15956529090136704
        },
        {
            "id": 1193,
            "name": "소프트웨어공학개론",
            "student_grade": 2,
            "semester": 1,
            "department_name": "소프트웨어공학과",
            "similarity": 0.13951934079798783
        },
        {
            "id": 1711,
            "name": "소프트웨어공학개론 1",
            "student_grade": 2,
            "semester": 1,
            "department_name": "소프트웨어공학과",
            "similarity": 0.1380384419883647
        },
        {
            "id": 354,
            "name": "데이터구조및프로그래밍실습",
            "student_grade": 2,
            "semester": 1,
            "department_name": "전자공학부",
            "similarity": 0.13414374764985815
        },
        {
            "id": 744,
            "name": "항공공학개론",
            "student_grade": 2,
            "semester": 1,
            "department_name": "항공우주공학과",
            "similarity": 0.12543330589997867
        },
        {
            "id": 3026,
            "name": "역학 2",
            "student_grade": 2,
            "semester": 2,
            "department_name": "물리학과",
            "similarity": 0.17411727147917777
        },
        {
            "id": 4491,
            "name": "금속공학실험 2",
            "student_grade": 2,
            "semester": 2,
            "department_name": "신소재공학부(금속시스템공학)",
            "similarity": 0.13915420768113376
        },
        {
            "id": 3482,
            "name": "약용식물조직배양학및실습 2",
            "student_grade": 2,
            "semester": 2,
            "department_name": "한약자원학과",
            "similarity": 0.1336569784663705
        },
        {
            "id": 3118,
            "name": "생태조경구조분석학",
            "student_grade": 2,
            "semester": 2,
            "department_name": "생태조경디자인학과",
            "similarity": 0.11457665042267683
        },
        {
            "id": 3081,
            "name": "공업역학",
            "student_grade": 2,
            "semester": 2,
            "department_name": "유기소재섬유공학과",
            "similarity": 0.11142190612146505
        },
        {
            "id": 2430,
            "name": "비행동역학",
            "student_grade": 3,
            "semester": 1,
            "department_name": "항공우주공학과",
            "similarity": 0.21246489954546444
        },
        {
            "id": 962,
            "name": "기계설계개론",
            "student_grade": 3,
            "semester": 1,
            "department_name": "융합기술공학부(IT융합기전공학)",
            "similarity": 0.1531678570582915
        },
        {
            "id": 716,
            "name": "소프트웨어개발프로세스",
            "student_grade": 3,
            "semester": 1,
            "department_name": "소프트웨어공학과",
            "similarity": 0.12555395849596798
        },
        {
            "id": 444,
            "name": "기계공학실험",
            "student_grade": 3,
            "semester": 1,
            "department_name": "기계공학과",
            "similarity": 0.1248147434226945
        },
        {
            "id": 1842,
            "name": "시스템시뮬레이션",
            "student_grade": 3,
            "semester": 1,
            "department_name": "산업정보시스템공학과",
            "similarity": 0.12023083398790464
        },
        {
            "id": 2819,
            "name": "소프트웨어공학",
            "student_grade": 3,
            "semester": 2,
            "department_name": "컴퓨터인공지능학부",
            "similarity": 0.20194621366409538
        },
        {
            "id": 3259,
            "name": "드론농업응용",
            "student_grade": 3,
            "semester": 2,
            "department_name": "생물산업기계공학과",
            "similarity": 0.16643329198993842
        },
        {
            "id": 4755,
            "name": "압축성유체역학",
            "student_grade": 3,
            "semester": 2,
            "department_name": "항공우주공학과",
            "similarity": 0.15763258429911534
        },
        {
            "id": 4169,
            "name": "항공기추진기관",
            "student_grade": 3,
            "semester": 2,
            "department_name": "항공우주공학과",
            "similarity": 0.12996937091035726
        },
        {
            "id": 4106,
            "name": "스마트농업프로그래밍",
            "student_grade": 3,
            "semester": 2,
            "department_name": "스마트팜학과",
            "similarity": 0.12404158126569523
        },
        {
            "id": 605,
            "name": "농업환경지리정보시스템",
            "student_grade": 4,
            "semester": 1,
            "department_name": "스마트팜학과",
            "similarity": 0.18465628310916937
        },
        {
            "id": 2126,
            "name": "소프트웨어공학캡스톤프로젝트",
            "student_grade": 4,
            "semester": 1,
            "department_name": "소프트웨어공학과",
            "similarity": 0.13567674732290794
        },
        {
            "id": 2156,
            "name": "화학공학종합설계",
            "student_grade": 4,
            "semester": 1,
            "department_name": "화학공학부",
            "similarity": 0.13412902661760395
        },
        {
            "id": 741,
            "name": "공정해석및설계",
            "student_grade": 4,
            "semester": 1,
            "department_name": "화학공학부",
            "similarity": 0.11959782633654945
        },
        {
            "id": 1784,
            "name": "풍력터빈공력설계",
            "student_grade": 4,
            "semester": 1,
            "department_name": "항공우주공학과",
            "similarity": 0.11349151738091458
        },
        {
            "id": 3275,
            "name": "항공드론융합설계",
            "student_grade": 4,
            "semester": 2,
            "department_name": "항공우주공학과",
            "similarity": 0.2134151037468553
        },
        {
            "id": 2702,
            "name": "바이오기기설계",
            "student_grade": 4,
            "semester": 2,
            "department_name": "기계설계공학부",
            "similarity": 0.12633472508611504
        },
        {
            "id": 4435,
            "name": "작물학세미나",
            "student_grade": 4,
            "semester": 2,
            "department_name": "작물생명과학과",
            "similarity": 0.10924170704668935
        }
    ]
}